ghost_pwa/__init__.py
ghost_pwa/ghost_pwa.py
ghost_pwa/icons/ghost-2.png
ghost_pwa/icons/ghost-4.png
ghost_pwa/manifest.webmanifest
ghost_pwa/sw.js
ghost_pwa/updateable_zip_file.py
ghost_pwa-2.0.4.dist-info/METADATA
ghost_pwa-2.0.4.dist-info/WHEEL
ghost_pwa-2.0.4.dist-info/RECORD
