Metadata-Version: 2.1
Name: ghost-pwa
Version: 2.0.4
Summary: 
Author: Patryk Kocielnik
Author-email: patryk@kocielnik.pl
Requires-Python: >=3.8,<4.0
Classifier: Programming Language :: Python :: 3
Classifier: Programming Language :: Python :: 3.8
Classifier: Programming Language :: Python :: 3.9
Classifier: Programming Language :: Python :: 3.10
Classifier: Programming Language :: Python :: 3.11
Requires-Dist: requests (>=2.28.1,<3.0.0)
